consoul/__init__.py
consoul/__main__.py
consoul/ai/__init__.py
consoul/ai/async_streaming.py
consoul/ai/context.py
consoul/ai/context_cache.py
consoul/ai/database.py
consoul/ai/environment.py
consoul/ai/exceptions.py
consoul/ai/history.py
consoul/ai/macos_fixes.py
consoul/ai/mlx_chat_wrapper.py
consoul/ai/models.py
consoul/ai/multimodal.py
consoul/ai/ollama_library.py
consoul/ai/prompt_builder.py
consoul/ai/providers.py
consoul/ai/reasoning.py
consoul/ai/streaming.py
consoul/ai/summarization.py
consoul/ai/title_generator.py
consoul/ai/tokenizers.py
consoul/ai/tools/__init__.py
consoul/ai/tools/approval.py
consoul/ai/tools/audit.py
consoul/ai/tools/base.py
consoul/ai/tools/cache.py
consoul/ai/tools/catalog.py
consoul/ai/tools/discovery.py
consoul/ai/tools/exceptions.py
consoul/ai/tools/implementations/__init__.py
consoul/ai/tools/implementations/analyze_images.py
consoul/ai/tools/implementations/bash.py
consoul/ai/tools/implementations/code_search.py
consoul/ai/tools/implementations/file_edit.py
consoul/ai/tools/implementations/file_matching.py
consoul/ai/tools/implementations/find_references.py
consoul/ai/tools/implementations/grep_search.py
consoul/ai/tools/implementations/read.py
consoul/ai/tools/implementations/read_url.py
consoul/ai/tools/implementations/web_search.py
consoul/ai/tools/implementations/wikipedia.py
consoul/ai/tools/parser.py
consoul/ai/tools/permissions/__init__.py
consoul/ai/tools/permissions/analyzer.py
consoul/ai/tools/permissions/policy.py
consoul/ai/tools/permissions/whitelist.py
consoul/ai/tools/presets.py
consoul/ai/tools/providers/__init__.py
consoul/ai/tools/providers/cli.py
consoul/ai/tools/registry.py
consoul/ai/tools/status.py
consoul/cli/__init__.py
consoul/cli/approval.py
consoul/cli/chat_session.py
consoul/cli/command_processor.py
consoul/cli/file_reader.py
consoul/cli/input.py
consoul/cli/stdin_reader.py
consoul/commands/__init__.py
consoul/commands/describe.py
consoul/commands/release.py
consoul/config/__init__.py
consoul-0.4.1.dist-info/LICENSE
consoul-0.4.1.dist-info/METADATA
consoul-0.4.1.dist-info/WHEEL
consoul-0.4.1.dist-info/entry_points.txt
consoul-0.4.1.dist-info/RECORD
