Metadata-Version: 2.3
Name: consoul
Version: 0.4.1
Summary: AI-powered terminal assistant with rich TUI - brings ChatGPT/Claude to your command line
License: Apache-2.0
Keywords: ai,assistant,terminal,tui,cli,chatgpt,claude,langchain,textual
Author: GoatBytes.IO
Author-email: jared@goatbytes.io
Maintainer: GoatBytes.IO
Maintainer-email: jared@goatbytes.io
Requires-Python: >=3.10
Classifier: Development Status :: 3 - Alpha
Classifier: Intended Audience :: Developers
Classifier: License :: OSI Approved :: Apache Software License
Classifier: Operating System :: OS Independent
Classifier: Programming Language :: Python :: 3
Classifier: Programming Language :: Python :: 3.10
Classifier: Programming Language :: Python :: 3.11
Classifier: Programming Language :: Python :: 3.12
Classifier: Programming Language :: Python :: 3.13
Classifier: Topic :: Software Development :: Libraries :: Python Modules
Classifier: Topic :: Terminals
Classifier: Topic :: Scientific/Engineering :: Artificial Intelligence
Classifier: Typing :: Typed
Provides-Extra: all
Provides-Extra: huggingface-local
Provides-Extra: huggingface-quantization
Provides-Extra: llamacpp
Provides-Extra: mlx
Provides-Extra: ollama-library
Provides-Extra: pdf
Provides-Extra: tui
Requires-Dist: accelerate (>=1.2.0) ; extra == "huggingface-local"
Requires-Dist: accelerate (>=1.2.0) ; extra == "huggingface-quantization"
Requires-Dist: beautifulsoup4 (>=4.12.0) ; extra == "all"
Requires-Dist: beautifulsoup4 (>=4.12.0) ; extra == "ollama-library"
Requires-Dist: bitsandbytes (>=0.45.0) ; extra == "huggingface-quantization"
Requires-Dist: click (>=8.3.1) ; extra == "all"
Requires-Dist: click (>=8.3.1) ; extra == "tui"
Requires-Dist: ddgs (>=9.9.0)
Requires-Dist: diskcache (>=5.6.3)
Requires-Dist: duckduckgo-search (>=8.1.1)
Requires-Dist: grep-ast (>=0.9.0)
Requires-Dist: langchain (>=1.0.7)
Requires-Dist: langchain-anthropic (>=1.0.4)
Requires-Dist: langchain-community (>=0.4.1,<0.5.0)
Requires-Dist: langchain-google-genai (>=3.0.3)
Requires-Dist: langchain-huggingface (>=1.0.1)
Requires-Dist: langchain-ollama (>=1.0.0)
Requires-Dist: langchain-openai (>=1.0.3)
Requires-Dist: llama-cpp-python (>=0.3.0) ; extra == "llamacpp"
Requires-Dist: mlx-lm (>=0.28.0) ; extra == "mlx"
Requires-Dist: pillow (>=10.0.0) ; extra == "all"
Requires-Dist: pillow (>=10.0.0) ; extra == "tui"
Requires-Dist: prompt-toolkit (>=3.0.52,<4.0.0)
Requires-Dist: pydantic (>=2.12.4)
Requires-Dist: pydantic-settings (>=2.12.0)
Requires-Dist: pypdf (>=6.2.0) ; extra == "all"
Requires-Dist: pypdf (>=6.2.0) ; extra == "pdf"
Requires-Dist: pyperclip (>=1.11.0) ; extra == "all"
Requires-Dist: pyperclip (>=1.11.0) ; extra == "tui"
Requires-Dist: python-dotenv (>=1.2.1)
Requires-Dist: pyyaml (>=6.0.3,<7.0.0)
Requires-Dist: requests (>=2.32.5)
Requires-Dist: rich (>=14.2.0)
Requires-Dist: textual (>=6.6.0) ; extra == "all"
Requires-Dist: textual (>=6.6.0) ; extra == "tui"
Requires-Dist: tiktoken (>=0.12.0)
Requires-Dist: torch (>=2.8.0) ; extra == "huggingface-local"
Requires-Dist: torch (>=2.8.0) ; extra == "huggingface-quantization"
Requires-Dist: trafilatura (>=2.0.0,<3.0.0)
Requires-Dist: transformers (>=4.45.0) ; extra == "huggingface-local"
Requires-Dist: transformers (>=4.45.0) ; extra == "huggingface-quantization"
Requires-Dist: tree-sitter (>=0.25.2)
Requires-Dist: tree-sitter-language-pack (>=0.11.0)
Requires-Dist: urllib3 (>=2.6.0)
Project-URL: Changelog, https://github.com/goatbytes/consoul/blob/main/CHANGELOG.md
Project-URL: Documentation, https://consoul.goatbytes.io
Project-URL: Homepage, https://github.com/goatbytes/consoul
Project-URL: Issues, https://github.com/goatbytes/consoul/issues
Project-URL: Repository, https://github.com/goatbytes/consoul
